randomdataset/__init__.py
randomdataset/__main__.py
randomdataset/_version.py
randomdataset/application.py
randomdataset/dataset.py
randomdataset/schemaparser.py
randomdataset/utils.py
randomdataset/fields/__init__.py
randomdataset/fields/basicfields.py
randomdataset/fields/fieldgen.py
randomdataset/generators/__init__.py
randomdataset/generators/csvgenerator.py
randomdataset/generators/generator.py
randomdataset-0.2.1.dist-info/LICENSE
randomdataset-0.2.1.dist-info/METADATA
randomdataset-0.2.1.dist-info/WHEEL
randomdataset-0.2.1.dist-info/entry_points.txt
randomdataset-0.2.1.dist-info/top_level.txt
randomdataset-0.2.1.dist-info/RECORD
