Metadata-Version: 2.1
Name: randomdataset
Version: 0.2.1
Summary: Random dataset generation tool
Home-page: https://github.com/KCL-BMEIS/RandomDataset
Author-email: Eric Kerfoot <eric.kerfoot@kcl.ac.uk>
License: MIT
Project-URL: homepage, https://github.com/KCL-BMEIS/RandomDataset
Platform: UNKNOWN
Requires-Python: >=3.7
License-File: LICENSE
Requires-Dist: numpy (>=1.18)
Requires-Dist: click
Requires-Dist: pyyaml
Requires-Dist: pandas
